orion/__init__.py
orion/agents/__init__.py
orion/agents/base_agent.py
orion/agents/normal_agent.py
orion/communications/__init__.py
orion/config/__init__.py
orion/factories/__init__.py
orion/factories/agents/__init__.py
orion/factories/agents/auto.py
orion/factories/agents/base_factory.py
orion/factories/clients/__init__.py
orion/factories/clients/simple.py
orion/llm_clients/__init__.py
orion/llm_clients/base_client.py
orion/llm_clients/openai_client.py
orion/llm_clients/supported_models.py
orion/utils/__init__.py
orion/utils/concurrency.py
orion/utils/logger.py
orion_core-0.1.0.dist-info/LICENSE
orion_core-0.1.0.dist-info/METADATA
orion_core-0.1.0.dist-info/WHEEL
orion_core-0.1.0.dist-info/top_level.txt
orion_core-0.1.0.dist-info/RECORD
