Metadata-Version: 2.2
Name: orion-core
Version: 0.1.0
Summary: A powerful multi-agent orchestration framework for LLMs
Author-email: Ashish Kumar Singh <ashishkmr472@gmail.com>
License: MIT
Project-URL: Homepage, https://github.com/ashishkumar/orion
Keywords: llm,multi-agent,framework,openai,gemini
Classifier: Programming Language :: Python :: 3.9
Classifier: License :: OSI Approved :: MIT License
Classifier: Operating System :: OS Independent
Requires-Python: >=3.9
License-File: LICENSE
Requires-Dist: pydantic<2.999,>=1.10
Requires-Dist: openai>=0.28.0
Requires-Dist: google-generativeai>=0.7.2
